bibla/__init__.py
bibla/__main__.py
bibla/bibla.yml
bibla/config.py
bibla/lint.py
bibla/rule.py
bibla/text_utils.py
bibla/rules/__init__.py
bibla/rules/database_rules.py
bibla/rules/entry_rules.py
bibla/rules/field_rules.py
bibla/rules/specification_rules.py
bibla/rules/text_rules.py
bibla-2.0.10.dist-info/licenses/LICENSE
bibla-2.0.10.dist-info/METADATA
bibla-2.0.10.dist-info/WHEEL
bibla-2.0.10.dist-info/entry_points.txt
bibla-2.0.10.dist-info/top_level.txt
bibla-2.0.10.dist-info/RECORD
