Metadata-Version: 2.4
Name: bibla
Version: 2.0.10
Summary: A minimalistic bibLaTeX linter by Tristan Cuvelier.
Home-page: https://github.com/MrClassicT/bibla
Author: Tristan Cuvelier
Author-email: tristan.cuvelier@student.hogent.be
License: MIT
Classifier: License :: OSI Approved :: MIT License
Classifier: Programming Language :: Python
Classifier: Programming Language :: Python :: 3
Classifier: Programming Language :: Python :: 3.7
Classifier: Programming Language :: Python :: 3.12
Classifier: Operating System :: OS Independent
License-File: LICENSE
Requires-Dist: click>=7
Requires-Dist: fuzzywuzzy>=0.10
Requires-Dist: markdown-table
Requires-Dist: pybtex==0.23.0
Requires-Dist: pyyaml>=5
Requires-Dist: unidecode<2,>=1
Requires-Dist: setuptools>=69.0.0
Provides-Extra: dev
Requires-Dist: anybadge; extra == "dev"
Requires-Dist: markdown; extra == "dev"
Requires-Dist: check-manifest; extra == "dev"
Requires-Dist: twine; extra == "dev"
Dynamic: author
Dynamic: author-email
Dynamic: classifier
Dynamic: description
Dynamic: description-content-type
Dynamic: home-page
Dynamic: license
Dynamic: license-file
Dynamic: provides-extra
Dynamic: requires-dist
Dynamic: summary
